poly_classifier/__init__.py
poly_classifier/__main__.py
poly_classifier/rooted_poly_decider.py
poly_classifier/unrooted_poly_decider.py
poly_classifier-0.0.1.dist-info/LICENSE
poly_classifier-0.0.1.dist-info/METADATA
poly_classifier-0.0.1.dist-info/WHEEL
poly_classifier-0.0.1.dist-info/top_level.txt
poly_classifier-0.0.1.dist-info/RECORD
