Metadata-Version: 2.1
Name: poly-classifier
Version: 0.0.1
Summary: A command-line tool for automatically classifying LCL problems on regular trees in the polynomial region.
License: Unlicense
Platform: UNKNOWN
Classifier: License :: OSI Approved :: The Unlicense (Unlicense)
Classifier: Programming Language :: Python :: 3
Classifier: Programming Language :: Python :: 3.9
License-File: LICENSE
Requires-Dist: rooted-tree-classifier
Requires-Dist: networkx
